Tareas/Tarea_2/cmos_cells.v
module BUF(A, Y);
  input A;
  output Y;
  assign #1 Y = A;
endmodule

module NOT(A, Y);
  input A;
  output Y;
  assign #2 Y = ~A;
endmodule

module NAND(A, B, Y);
  input A, B;
  output Y;
  assign #3 Y = ~(A & B);
endmodule

module NOR(A, B, Y);
  input A, B;
  output Y;
  assign #1 Y = ~(A | B);
endmodule

module DFF(C, D, Q);
  input C, D; 
  output reg Q;
  always @(posedge C) #2 Q <= D;
endmodule

Tareas/Tarea_2/modoContador_tester.v
module modoTester (clk, rst, enable, modo, d, q, rco);

output reg clk, rst, enable;
output reg [1:0] modo;
output reg [3:0] d;
input [3:0] q;
input rco;

initial begin
    clk = 0;
    enable =1;
    rst = 0;
    //Prueba #1 Cuentas ascendente
      d = 0;
      modo = 3;
      #2 modo = 0;
      //#2 enable = 0;
      //#10 enable = 1;
      #36 rst = 1;
      #6 rst = 0;
    //Prueba #2 Cuentas descendente -1
      #66 modo = 1;
      #2 enable = 0;
      #10 enable = 1;
      #36 rst = 1;
      #6 rst = 0;
    //Prueba #3 Cuentas descendente -3
      #64 modo = 3;
      #6 d=14;
      modo = 2;
      #36 rst = 1;
      #6 rst = 0;
      #2 enable = 0;
      #4 enable = 1;
      #12 modo = 3;
    //Prueba #4 Carga en paralelo
      #2 d = 2;
      #2 d = 4;
      #2 enable = 0;
      #10 enable = 1;
      #2 d = 6;
      #2 d = 8;
      #2 d = 10;
      #2 rst = 1;
      #6 rst = 0;
      #2 d = 14;
      #2 d = 15;
    #4 $finish;
  end

  always begin
  #1 clk = !clk;
  end
endmodule

Tareas/Tarea_2/modoContador.v
module
    MODO (clk,
    rst,
    enable,
    modo,
    d,
    q,
    rco);
    input clk, rst, enable;
    input [1:0] modo;
    input [3:0] d;
    output reg [3:0] q;
    output reg rco;
    
    always @(*) begin
        if (rst) begin
            rco <= 0;
            case (modo)
                2'b00: q <= 4'b0;
                2'b01: q <= 4'b1111;
                2'b10: q <= 4'b1111;
                2'b11: begin
                    q   <= 4'bXXXX;
                    rco <= clk;
                end
            endcase
        end
    end
    always @(posedge clk) begin
        if (rst) rco = 0;
        else if (enable) begin
            case (modo)
                0: begin
                    rco <= (q > 14) ? 1 : 0;
                    q   <= (q + 1);
                end
                1: if (q > 0) q <= (q - 1);
                else begin
                    q   <= 15;
                    rco <= 1;
                end
                2: if (q > 2) q <= (q - 3);
                else begin
                    case (q)
                        0: q <= 12;
                        1: q <= 13;
                        2: q <= 14;
                    endcase
                    rco <= 1;
                end
                3: begin
                    q   <= d;
                    rco <= clk;
                end
            endcase
        end
    end
endmodule

Tareas/Tarea_2/modoContador_tb.v
//`include "modo_full_synth.v"
`include "cmos_cells.v"
`include "modoContador.v"
`include "modoContador_tester.v"

//Testbench Code
module counter_tb;

wire clk, rst, enable;
wire [1:0] modo;
wire [3:0] d;
wire [3:0] q;
wire rco;

MODO U1(
  .clk(clk),
  .rst(rst),
  .enable(enable),
  .modo(modo),
  .d(d),
  .q(q),
  .rco(rco)
);

modoTester T1(
  .clk(clk),
  .rst(rst),
  .enable(enable),
  .modo(modo),
  .d(d),
  .q(q),
  .rco(rco)
);

initial begin
  $dumpfile("resultados.vcd");
  $dumpvars(-1, U1);
  $monitor ("clk=%b, rst=%b, enable=%b, modo=%b, d=%b, q=%b, rco=%b", clk, rst, enable, modo, d, q, rco);
  //$monitor("b", q);
end
endmodule

Tareas/Tarea_2/resultados.vcd
$date
	Fri Sep 23 12:50:42 2022
$end
$version
	Icarus Verilog
$end
$timescale
	1s
$end
$scope module counter_tb $end
$scope module U1 $end
$var wire 1 ! clk $end
$var wire 4 " d [3:0] $end
$var wire 1 # enable $end
$var wire 2 $ modo [1:0] $end
$var wire 1 % rst $end
$var reg 4 & q [3:0] $end
$var reg 1 ' rco $end
$upscope $end
$upscope $end
$enddefinitions $end
#0
$dumpvars
x'
bx &
0%
b11 $
1#
b0 "
0!
$end
#1
1'
b0 &
1!
#2
0!
b0 $
#3
b1 &
0'
1!
#4
0!
#5
b10 &
1!
#6
0!
#7
b11 &
1!
#8
0!
#9
b100 &
1!
#10
0!
#11
b101 &
1!
#12
0!
#13
b110 &
1!
#14
0!
#15
b111 &
1!
#16
0!
#17
b1000 &
1!
#18
0!
#19
b1001 &
1!
#20
0!
#21
b1010 &
1!
#22
0!
#23
b1011 &
1!
#24
0!
#25
b1100 &
1!
#26
0!
#27
b1101 &
1!
#28
0!
#29
b1110 &
1!
#30
0!
#31
b1111 &
1!
#32
0!
#33
b0 &
1'
1!
#34
0!
#35
b1 &
0'
1!
#36
0!
#37
b10 &
1!
#38
b0 &
0!
1%
#39
1!
#40
0!
#41
1!
#42
0!
#43
1!
#44
0!
0%
#45
b1 &
1!
#46
0!
#47
b10 &
1!
#48
0!
#49
b11 &
1!
#50
0!
#51
b100 &
1!
#52
0!
#53
b101 &
1!
#54
0!
#55
b110 &
1!
#56
0!
#57
b111 &
1!
#58
0!
#59
b1000 &
1!
#60
0!
#61
b1001 &
1!
#62
0!
#63
b1010 &
1!
#64
0!
#65
b1011 &
1!
#66
0!
#67
b1100 &
1!
#68
0!
#69
b1101 &
1!
#70
0!
#71
b1110 &
1!
#72
0!
#73
b1111 &
1!
#74
0!
#75
b0 &
1'
1!
#76
0!
#77
b1 &
0'
1!
#78
0!
#79
b10 &
1!
#80
0!
#81
b11 &
1!
#82
0!
#83
b100 &
1!
#84
0!
#85
b101 &
1!
#86
0!
#87
b110 &
1!
#88
0!
#89
b111 &
1!
#90
0!
#91
b1000 &
1!
#92
0!
#93
b1001 &
1!
#94
0!
#95
b1010 &
1!
#96
0!
#97
b1011 &
1!
#98
0!
#99
b1100 &
1!
#100
0!
#101
b1101 &
1!
#102
0!
#103
b1110 &
1!
#104
0!
#105
b1111 &
1!
#106
0!
#107
b0 &
1'
1!
#108
0!
#109
b1 &
0'
1!
#110
0!
b1 $
#111
b0 &
1!
#112
0!
0#
#113
1!
#114
0!
#115
1!
#116
0!
#117
1!
#118
0!
#119
1!
#120
0!
#121
1!
#122
0!
1#
#123
1'
b1111 &
1!
#124
0!
#125
b1110 &
1!
#126
0!
#127
b1101 &
1!
#128
0!
#129
b1100 &
1!
#130
0!
#131
b1011 &
1!
#132
0!
#133
b1010 &
1!
#134
0!
#135
b1001 &
1!
#136
0!
#137
b1000 &
1!
#138
0!
#139
b111 &
1!
#140
0!
#141
b110 &
1!
#142
0!
#143
b101 &
1!
#144
0!
#145
b100 &
1!
#146
0!
#147
b11 &
1!
#148
0!
#149
b10 &
1!
#150
0!
#151
b1 &
1!
#152
0!
#153
b0 &
1!
#154
0!
#155
b1111 &
1!
#156
0!
#157
b1110 &
1!
#158
b1111 &
0'
0!
1%
#159
1!
#160
0!
#161
1!
#162
0!
#163
1!
#164
0!
0%
#165
b1110 &
1!
#166
0!
#167
b1101 &
1!
#168
0!
#169
b1100 &
1!
#170
0!
#171
b1011 &
1!
#172
0!
#173
b1010 &
1!
#174
0!
#175
b1001 &
1!
#176
0!
#177
b1000 &
1!
#178
0!
#179
b111 &
1!
#180
0!
#181
b110 &
1!
#182
0!
#183
b101 &
1!
#184
0!
#185
b100 &
1!
#186
0!
#187
b11 &
1!
#188
0!
#189
b10 &
1!
#190
0!
#191
b1 &
1!
#192
0!
#193
b0 &
1!
#194
0!
#195
1'
b1111 &
1!
#196
0!
#197
b1110 &
1!
#198
0!
#199
b1101 &
1!
#200
0!
#201
b1100 &
1!
#202
0!
#203
b1011 &
1!
#204
0!
#205
b1010 &
1!
#206
0!
#207
b1001 &
1!
#208
0!
#209
b1000 &
1!
#210
0!
#211
b111 &
1!
#212
0!
#213
b110 &
1!
#214
0!
#215
b101 &
1!
#216
0!
#217
b100 &
1!
#218
0!
#219
b11 &
1!
#220
0!
#221
b10 &
1!
#222
0!
#223
b1 &
1!
#224
0!
#225
b0 &
1!
#226
0!
#227
b1111 &
1!
#228
0!
b11 $
#229
b0 &
1!
#230
0!
#231
1!
#232
0!
#233
1!
#234
0!
b10 $
b1110 "
#235
b1100 &
1!
#236
0!
#237
b1001 &
1!
#238
0!
#239
b110 &
1!
#240
0!
#241
b11 &
1!
#242
0!
#243
b0 &
1!
#244
0!
#245
b1100 &
1!
#246
0!
#247
b1001 &
1!
#248
0!
#249
b110 &
1!
#250
0!
#251
b11 &
1!
#252
0!
#253
b0 &
1!
#254
0!
#255
b1100 &
1!
#256
0!
#257
b1001 &
1!
#258
0!
#259
b110 &
1!
#260
0!
#261
b11 &
1!
#262
0!
#263
b0 &
1!
#264
0!
#265
b1100 &
1!
#266
0!
#267
b1001 &
1!
#268
0!
#269
b110 &
1!
#270
b1111 &
0'
0!
1%
#271
1!
#272
0!
#273
1!
#274
0!
#275
1!
#276
0!
0%
#277
b1100 &
1!
#278
0!
0#
#279
1!
#280
0!
#281
1!
#282
0!
1#
#283
b1001 &
1!
#284
0!
#285
b110 &
1!
#286
0!
#287
b11 &
1!
#288
0!
#289
b0 &
1!
#290
0!
#291
1'
b1100 &
1!
#292
0!
#293
b1001 &
1!
#294
0!
b11 $
#295
b1110 &
1!
#296
0!
b10 "
#297
b10 &
1!
#298
0!
b100 "
#299
b100 &
1!
#300
0!
0#
#301
1!
#302
0!
#303
1!
#304
0!
#305
1!
#306
0!
#307
1!
#308
0!
#309
1!
#310
0!
1#
#311
1!
#312
0!
b110 "
#313
b110 &
1!
#314
0!
b1000 "
#315
b1000 &
1!
#316
0!
b1010 "
#317
b1010 &
1!
#318
bx &
0'
0!
1%
#319
1'
1!
#320
0'
0!
#321
1'
1!
#322
0'
0!
#323
1'
1!
#324
0!
0%
#325
b1010 &
1!
#326
0!
b1110 "
#327
b1110 &
1!
#328
0!
b1111 "
#329
b1111 &
1!
