Tareas/Tarea_2/modoContador_tester.v
module modoTester (clk, rst, enable, modo, d, q, rco);

output reg clk, rst, enable;
output reg [1:0] modo;
output reg [3:0] d;
input [3:0] q;
input rco;

initial begin
    clk = 0;
    enable =1;
    rst = 0;
    //Prueba #1 Cuentas ascendente
      d = 0;
      modo = 3;
      #2 modo = 0;
      //#2 enable = 0;
      //#10 enable = 1;
      #36 rst = 1;
      #6 rst = 0;
    //Prueba #2 Cuentas descendente -1
      #66 modo = 1;
      #2 enable = 0;
      #10 enable = 1;
      #36 rst = 1;
      #6 rst = 0;
    //Prueba #3 Cuentas descendente -3
      #64 modo = 3;
      #6 d=14;
      modo = 2;
      #36 rst = 1;
      #6 rst = 0;
      #2 enable = 0;
      #4 enable = 1;
      #12 modo = 3;
    //Prueba #4 Carga en paralelo
      #2 d = 2;
      #2 d = 4;
      #2 enable = 0;
      #10 enable = 1;
      #2 d = 6;
      #2 d = 8;
      #2 d = 10;
      #2 rst = 1;
      #6 rst = 0;
      #2 d = 14;
      #2 d = 15;
    #4 $finish;
  end

  always begin
  #1 clk = !clk;
  end
endmodule

Tareas/Tarea_1/modoContador.v
module MODO (clk, rst, enable, modo, d, q, rco);

input clk, rst, enable;
input [1:0] modo;
input [3:0] d;
output reg [3:0] q;
output reg rco;

always @ (posedge clk or posedge rst or posedge enable or d) begin
  if (rco !== 1) rco <= 0;
  if (rst) begin 
    rco <= 0;
    case (modo)
      0: q <= 0; 
      1: q <= 15;
      2: q <= 15; 
      3: q <= 4'bXXXX; endcase
  end else begin
    while (enable) begin
      case (modo)
        0: if(rco) q = rco;
          else if (q < 15) q <= (q + 1); 
          else begin
            q <=0;
            rco <= 1; end
        1: if (q > 0) q <= (q - 1); 
          else begin
            q <=15;
            rco <= 1; end
        2: if (q > 2) q <= (q - 3); 
          else begin
            case (q)
              0: q <= 12;
              1: q <= 13;
              2: q <=14; endcase
          rco <= 1; end 
        3: q <= d;
      endcase
      if (rco == 1) rco = 0;
    end
  end
end
endmodule

Tareas/Tarea_1/modoContador_tb.v
`include "modoContador.v"
`include "modoContador_tester.v"
//Testbench Code
module counter_tb;

wire clk, rst, enable;
wire [1:0] modo;
wire [3:0] d;
wire [3:0] q;
wire rco;

MODO U1(
  .clk(clk),
  .rst(rst),
  .enable(enable),
  .modo(modo),
  .d(d),
  .q(q),
  .rco(rco)
);

modoTester T1(
  .clk(clk),
  .rst(rst),
  .enable(enable),
  .modo(modo),
  .d(d),
  .q(q),
  .rco(rco)
);

initial begin
  $dumpfile("resultados.vcd");
  $dumpvars(-1, U1);
  $monitor ("clk=%b, rst=%b, enable=%b, modo=%b, d=%b, q=%b, rco=%b", clk, rst, enable, modo, d, q, rco);
  //$monitor("b", q);
end
endmodule

Tareas/Tarea_1/resultados.vcd
$date
	Thu Sep 22 20:42:53 2022
$end
$version
	Icarus Verilog
$end
$timescale
	1s
$end
$scope module counter_tb $end
$scope module U1 $end
$var wire 1 ! clk $end
$var wire 4 " d [3:0] $end
$var wire 1 # enable $end
$var wire 2 $ modo [1:0] $end
$var wire 1 % rst $end
$var reg 4 & q [3:0] $end
$var reg 1 ' rco $end
$scope begin COUNT $end
$upscope $end
$upscope $end
$upscope $end
$enddefinitions $end
#0
$dumpvars
0'
b0 &
0%
b11 $
1#
b0 "
0!
$end
#1
1!
#2
0!
b0 $
#3
b1 &
1!
#4
0!
0#
#5
1!
#6
0!
#7
1!
#8
0!
#9
1!
#10
0!
#11
1!
#12
0!
#13
1!
#14
b10 &
0!
1#
#15
b11 &
1!
#16
0!
#17
b100 &
1!
#18
0!
#19
b101 &
1!
#20
0!
#21
b110 &
1!
#22
0!
#23
b111 &
1!
#24
0!
#25
b1000 &
1!
#26
0!
#27
b1001 &
1!
#28
0!
#29
b1010 &
1!
#30
0!
#31
b1011 &
1!
#32
0!
#33
b1100 &
1!
#34
0!
#35
b1101 &
1!
#36
0!
#37
b1110 &
1!
#38
0!
#39
b1111 &
1!
#40
0!
#41
1'
b0 &
1!
#42
0!
#43
0'
b1 &
1!
#44
0!
#45
b10 &
1!
#46
0!
#47
b11 &
1!
#48
0!
#49
b100 &
1!
#50
b0 &
0!
1%
#51
1!
#52
0!
0%
#53
b1 &
1!
#54
0!
#55
b10 &
1!
#56
0!
#57
b11 &
1!
#58
0!
#59
b100 &
1!
#60
0!
#61
b101 &
1!
#62
0!
#63
b110 &
1!
#64
0!
#65
b111 &
1!
#66
0!
#67
b1000 &
1!
#68
0!
#69
b1001 &
1!
#70
0!
#71
b1010 &
1!
#72
0!
#73
b1011 &
1!
#74
0!
#75
b1100 &
1!
#76
0!
#77
b1101 &
1!
#78
0!
#79
b1110 &
1!
#80
0!
#81
b1111 &
1!
#82
0!
#83
1'
b0 &
1!
#84
0!
#85
0'
b1 &
1!
#86
0!
#87
b10 &
1!
#88
0!
#89
b11 &
1!
#90
0!
#91
b100 &
1!
#92
0!
#93
b101 &
1!
#94
0!
#95
b110 &
1!
#96
0!
#97
b111 &
1!
#98
0!
#99
b1000 &
1!
#100
0!
#101
b1001 &
1!
#102
0!
#103
b1010 &
1!
#104
0!
#105
b1011 &
1!
#106
0!
#107
b1100 &
1!
#108
0!
#109
b1101 &
1!
#110
0!
#111
b1110 &
1!
#112
0!
#113
b1111 &
1!
#114
0!
#115
1'
b0 &
1!
#116
0!
#117
0'
b1 &
1!
#118
0!
b1 $
#119
b0 &
1!
#120
0!
0#
#121
1!
#122
0!
#123
1!
#124
0!
#125
1!
#126
0!
#127
1!
#128
0!
#129
1!
#130
1'
b1111 &
0!
1#
#131
b1110 &
0'
1!
#132
0!
#133
b1101 &
1!
#134
0!
#135
b1100 &
1!
#136
0!
#137
b1011 &
1!
#138
0!
#139
b1010 &
1!
#140
0!
#141
b1001 &
1!
#142
0!
#143
b1000 &
1!
#144
0!
#145
b111 &
1!
#146
0!
#147
b110 &
1!
#148
0!
#149
b101 &
1!
#150
0!
#151
b100 &
1!
#152
0!
#153
b11 &
1!
#154
0!
#155
b10 &
1!
#156
0!
#157
b1 &
1!
#158
0!
#159
b0 &
1!
#160
0!
#161
1'
b1111 &
1!
#162
0!
#163
b1110 &
0'
1!
#164
0!
#165
b1101 &
1!
#166
b1111 &
0!
1%
#167
1!
#168
0!
0%
#169
b1110 &
1!
#170
0!
#171
b1101 &
1!
#172
0!
#173
b1100 &
1!
#174
0!
#175
b1011 &
1!
#176
0!
#177
b1010 &
1!
#178
0!
#179
b1001 &
1!
#180
0!
#181
b1000 &
1!
#182
0!
#183
b111 &
1!
#184
0!
#185
b110 &
1!
#186
0!
#187
b101 &
1!
#188
0!
#189
b100 &
1!
#190
0!
#191
b11 &
1!
#192
0!
#193
b10 &
1!
#194
0!
#195
b1 &
1!
#196
0!
#197
b0 &
1!
#198
0!
#199
1'
b1111 &
1!
#200
0!
#201
b1110 &
0'
1!
#202
0!
#203
b1101 &
1!
#204
0!
#205
b1100 &
1!
#206
0!
#207
b1011 &
1!
#208
0!
#209
b1010 &
1!
#210
0!
#211
b1001 &
1!
#212
0!
#213
b1000 &
1!
#214
0!
#215
b111 &
1!
#216
0!
#217
b110 &
1!
#218
0!
#219
b101 &
1!
#220
0!
#221
b100 &
1!
#222
0!
#223
b11 &
1!
#224
0!
#225
b10 &
1!
#226
0!
#227
b1 &
1!
#228
0!
#229
b0 &
1!
#230
0!
#231
1'
b1111 &
1!
#232
0!
b11 $
#233
b0 &
0'
1!
#234
0!
#235
1!
#236
0!
#237
1!
#238
1'
b1100 &
0!
b10 $
b1110 "
#239
b1001 &
0'
1!
#240
0!
#241
b110 &
1!
#242
0!
#243
b11 &
1!
#244
0!
#245
b0 &
1!
#246
0!
#247
1'
b1100 &
1!
#248
0!
#249
b1001 &
0'
1!
#250
0!
#251
b110 &
1!
#252
0!
#253
b11 &
1!
#254
0!
#255
b0 &
1!
#256
0!
#257
1'
b1100 &
1!
#258
0!
#259
b1001 &
0'
1!
#260
0!
#261
b110 &
1!
#262
0!
#263
b11 &
1!
#264
0!
#265
b0 &
1!
#266
0!
#267
1'
b1100 &
1!
#268
0!
#269
b1001 &
0'
1!
#270
0!
#271
b110 &
1!
#272
0!
#273
b11 &
1!
#274
b1111 &
0!
1%
#275
1!
#276
0!
0%
#277
b1100 &
1!
#278
0!
0#
#279
1!
#280
0!
#281
1!
#282
b1001 &
0!
1#
#283
b110 &
1!
#284
0!
#285
b11 &
1!
#286
0!
#287
b0 &
1!
#288
0!
#289
1'
b1100 &
1!
#290
0!
#291
b1001 &
0'
1!
#292
0!
#293
b110 &
1!
#294
0!
b11 $
#295
b1110 &
1!
#296
b10 &
0!
b10 "
#297
1!
#298
b100 &
0!
b100 "
#299
1!
#300
0!
0#
#301
1!
#302
0!
#303
1!
#304
0!
#305
1!
#306
0!
#307
1!
#308
0!
#309
1!
#310
0!
1#
#311
1!
#312
b110 &
0!
b110 "
#313
1!
#314
b1000 &
0!
b1000 "
#315
1!
#316
b1010 &
0!
b1010 "
#317
1!
#318
bx &
0!
1%
#319
1!
#320
0!
0%
#321
b1010 &
1!
#322
b1110 &
0!
b1110 "
#323
1!
#324
b1111 &
0!
b1111 "
